{
  "main": {
    "syr": {
      "identity": {
        "language": "syr"
      },
      "numbers": {
        "currencies": {
          "AFN": {
            "symbol-alt-narrow": "؋"
          },
          "AMD": {
            "displayName": "ܕܪܗܡ ܕܐܪܡܢܝܐ",
            "displayName-count-one": "ܕܪܗܡ ܕܐܪܡܢܝܐ",
            "displayName-count-other": "ܕܪ̈ܗܡܐ ܕܐܪܡܢܝܐ",
            "symbol-alt-narrow": "֏"
          },
          "ANG": {
            "displayName": "ܦܠܘܪܝܢ ܐܢܬܝܠܝܣܝܐ ܕܗܘܠܢܕܐ",
            "displayName-count-one": "ܦܠܘܪܝܢ ܐܢܬܝܠܝܣܝܐ ܕܗܘܠܢܕܐ",
            "displayName-count-other": "ܦܠܘܪ̈ܝܢܐ ܐܢܬܝܠܝܣܝܐ ܕܗܘܠܢܕܐ"
          },
          "AOA": {
            "symbol-alt-narrow": "Kz"
          },
          "ARS": {
            "displayName": "ܦܝܣܘ ܕܐܪܓܢܬܝܢܐ",
            "displayName-count-one": "ܦܝܣܘ ܕܐܪܓܢܬܝܢܐ",
            "displayName-count-other": "ܦܝ̈ܣܘܣ ܕܐܪܓܢܬܝܢܐ",
            "symbol-alt-narrow": "$"
          },
          "AUD": {
            "displayName": "ܕܘܠܪ ܕܐܘܣܬܪܠܝܐ",
            "displayName-count-one": "ܕܘܠܪ ܕܐܘܣܬܪܠܝܐ",
            "displayName-count-other": "ܕܘܠܪ̈ܐ ܕܐܘܣܬܪܠܝܐ",
            "symbol": "A$",
            "symbol-alt-narrow": "$"
          },
          "AWG": {
            "displayName": "ܦܠܘܪܝܢ ܕܐܪܘܒܐ",
            "displayName-count-one": "ܦܠܘܪܝܢ ܕܐܪܘܒܐ",
            "displayName-count-other": "ܦܠܘܪ̈ܝܢܐ ܕܐܪܘܒܐ"
          },
          "AZN": {
            "symbol-alt-narrow": "₼"
          },
          "BAM": {
            "symbol-alt-narrow": "KM"
          },
          "BBD": {
            "displayName": "ܕܘܠܪ ܕܒܪܒܐܕܘܣ",
            "displayName-count-one": "ܕܘܠܪ ܕܒܪܒܐܕܘܣ",
            "displayName-count-other": "ܕܘܠܪ̈ܐ ܕܒܪܒܐܕܘܣ",
            "symbol-alt-narrow": "$"
          },
          "BDT": {
            "symbol-alt-narrow": "৳"
          },
          "BHD": {
            "displayName": "ܕܝܢܪܐ ܕܒܚܪܝܢ",
            "displayName-count-one": "ܕܝܢܪܐ ܕܒܚܪܝܢ",
            "displayName-count-other": "ܕܝܢܪ̈ܐ ܕܒܚܪܝܢ"
          },
          "BMD": {
            "displayName": "ܕܘܠܪ ܕܒܝܪܡܘܕܐ",
            "displayName-count-one": "ܕܘܠܪ ܕܒܝܪܡܘܕܐ",
            "displayName-count-other": "ܕܘܠܪ̈ܐ ܕܒܝܪܡܘܕܐ",
            "symbol-alt-narrow": "$"
          },
          "BND": {
            "displayName": "ܕܘܠܪ ܕܒܪܘܢܐܝ",
            "displayName-count-one": "ܕܘܠܪ ܕܒܪܘܢܐܝ",
            "displayName-count-other": "ܕܘܠܪ̈ܐ ܕܒܪܘܢܐܝ",
            "symbol-alt-narrow": "$"
          },
          "BOB": {
            "symbol-alt-narrow": "Bs"
          },
          "BRL": {
            "symbol": "R$",
            "symbol-alt-narrow": "R$"
          },
          "BSD": {
            "displayName": "ܕܘܠܪ ܕܒܗܐܡܣ",
            "displayName-count-one": "ܕܘܠܪ ܕܒܗܐܡܣ",
            "displayName-count-other": "ܕܘܠܪ̈ܐ ܕܒܗܐܡܣ",
            "symbol-alt-narrow": "$"
          },
          "BWP": {
            "symbol-alt-narrow": "P"
          },
          "BZD": {
            "displayName": "ܕܘܠܪ ܕܒܠܝܙ",
            "displayName-count-one": "ܕܘܠܪ ܕܒܠܝܙ",
            "displayName-count-other": "ܕܘܠܪ̈ܐ ܕܒܠܝܙ",
            "symbol-alt-narrow": "$"
          },
          "CAD": {
            "displayName": "ܕܘܠܪ ܕܟܢܕܐ",
            "displayName-count-one": "ܕܘܠܪ ܕܟܢܕܐ",
            "displayName-count-other": "ܕܘܠܪ̈ܐ ܕܟܢܕܐ",
            "symbol": "CA$",
            "symbol-alt-narrow": "$"
          },
          "CLP": {
            "symbol-alt-narrow": "$"
          },
          "CNY": {
            "displayName": "ܝܘܐܢ ܕܨܝܢ",
            "displayName-count-one": "ܝܘܐܢ ܕܨܝܢ",
            "displayName-count-other": "ܝܘܐܢ̈ܐ ܕܨܝܢ",
            "symbol": "CN¥",
            "symbol-alt-narrow": "¥"
          },
          "COP": {
            "displayName": "ܦܝܣܘ ܕܟܘܠܘܡܒܝܐ",
            "displayName-count-one": "ܦܝܣܘ ܕܟܘܠܘܡܒܝܐ",
            "displayName-count-other": "ܦܝ̈ܣܘܣ ܕܟܘܠܘܡܒܝܐ",
            "symbol-alt-narrow": "$"
          },
          "CRC": {
            "displayName": "ܟܘܠܘܢ ܕܟܘܣܬܐ ܪܝܟܐ",
            "displayName-count-one": "ܟܘܠܘܢ ܕܟܘܣܬܐ ܪܝܟܐ",
            "displayName-count-other": "ܟܘܠܘܢ̈ܐ ܕܟܘܣܬܐ ܪܝܟܐ",
            "symbol-alt-narrow": "₡"
          },
          "CUC": {
            "displayName": "ܦܝܣܘ ܡܬܥܪܦܢܝܬܐ ܕܩܘܒܐ",
            "displayName-count-one": "ܦܝܣܘ ܡܬܥܪܦܢܝܬܐ ܕܩܘܒܐ",
            "displayName-count-other": "ܦܝ̈ܣܘܣ ܡܬܥܪ̈ܦܢܝܬܐ ܕܩܘܒܐ",
            "symbol-alt-narrow": "$"
          },
          "CUP": {
            "displayName": "ܦܝܣܘ ܕܩܘܒܐ",
            "displayName-count-one": "ܦܝܣܘ ܕܩܘܒܐ",
            "displayName-count-other": "ܦܝ̈ܣܘܣ ܕܩܘܒܐ",
            "symbol-alt-narrow": "$"
          },
          "CZK": {
            "symbol-alt-narrow": "Kč"
          },
          "DKK": {
            "symbol-alt-narrow": "kr"
          },
          "DOP": {
            "displayName": "ܦܝܣܘ ܕܕܘܡܝܢܝܟܐܢ",
            "displayName-count-one": "ܦܝܣܘ ܕܕܘܡܝܢܝܟܐܢ",
            "displayName-count-other": "ܦܝ̈ܣܘܣ ܕܕܘܡܝܢܝܟܐܢ",
            "symbol-alt-narrow": "$"
          },
          "DZD": {
            "displayName": "ܕܝܢܪܐ ܕܓܙܐܪ",
            "displayName-count-one": "ܕܝܢܪܐ ܕܓܙܐܪ",
            "displayName-count-other": "ܕܝܢܪ̈ܐ ܕܓܙܐܪ"
          },
          "EGP": {
            "displayName": "ܠܝܛܪܐ ܕܡܨܪܝܢ",
            "displayName-count-one": "ܠܝܛܪܐ ܕܡܨܪܝܢ",
            "displayName-count-other": "ܠܝܛܪ̈ܐ ܕܡܨܪܝܢ",
            "symbol-alt-narrow": "E£"
          },
          "ESP": {
            "symbol-alt-narrow": "₧"
          },
          "EUR": {
            "displayName": "ܐܘܪܘ",
            "displayName-count-one": "ܐܘܪܘ",
            "displayName-count-other": "ܐܘܪ̈ܘܣ",
            "symbol": "€",
            "symbol-alt-narrow": "€"
          },
          "FJD": {
            "displayName": "ܕܘܠܪ ܕܦܝܓܝ",
            "displayName-count-one": "ܕܘܠܪ ܕܦܝܓܝ",
            "displayName-count-other": "ܕܘܠܪ̈ܐ ܕܦܝܓܝ",
            "symbol-alt-narrow": "$"
          },
          "FKP": {
            "displayName": "ܠܝܛܪܐ ܕܓܙܪ̈ܬܐ ܕܦܠܟܠܢܕ",
            "displayName-count-one": "ܠܝܛܪܐ ܕܓܙܪ̈ܬܐ ܕܦܠܟܠܢܕ",
            "displayName-count-other": "ܠܝܛܪ̈ܐ ܕܓܙܪ̈ܬܐ ܕܦܠܟܠܢܕ",
            "symbol-alt-narrow": "£"
          },
          "GBP": {
            "symbol": "£",
            "symbol-alt-narrow": "£"
          },
          "GEL": {
            "symbol-alt-narrow": "₾"
          },
          "GHS": {
            "symbol-alt-narrow": "GH₵"
          },
          "GIP": {
            "displayName": "ܠܝܛܪܐ ܕܓܒܪܠܛܪ",
            "displayName-count-one": "ܠܝܛܪܐ ܕܓܒܪܠܛܪ",
            "displayName-count-other": "ܠܝܛܪ̈ܐ ܕܓܒܪܠܛܪ",
            "symbol-alt-narrow": "£"
          },
          "GNF": {
            "symbol-alt-narrow": "FG"
          },
          "GTQ": {
            "displayName": "ܟܝܬܙܠ ܕܓܘܐܬܝܡܐܠܐ",
            "displayName-count-one": "ܟܝܬܙܠ ܕܓܘܐܬܝܡܐܠܐ",
            "displayName-count-other": "ܟܝܬܙ̈ܠܐ ܕܓܘܐܬܝܡܐܠܐ",
            "symbol-alt-narrow": "Q"
          },
          "GYD": {
            "displayName": "ܕܘܠܪ ܕܓܘܝܐܢܐ",
            "displayName-count-one": "ܕܘܠܪ ܕܓܘܝܐܢܐ",
            "displayName-count-other": "ܕܘܠܪ̈ܐ ܕܓܘܝܐܢܐ",
            "symbol-alt-narrow": "$"
          },
          "HKD": {
            "displayName": "ܕܘܠܪ ܕܗܘܢܓ ܟܘܢܓ",
            "displayName-count-one": "ܕܘܠܪ ܕܗܘܢܓ ܟܘܢܓ",
            "displayName-count-other": "ܕܘܠܪ̈ܐ ܕܗܘܢܓ ܟܘܢܓ",
            "symbol": "HK$",
            "symbol-alt-narrow": "$"
          },
          "HNL": {
            "displayName": "ܠܝܡܦܝܪܐ ܕܗܘܢܕܘܪܣ",
            "displayName-count-one": "ܠܝܡܦܝܪܐ ܕܗܘܢܕܘܪܣ",
            "displayName-count-other": "ܠܝܡܦܝܪ̈ܐ ܕܗܘܢܕܘܪܣ",
            "symbol-alt-narrow": "L"
          },
          "HRK": {
            "symbol-alt-narrow": "kn"
          },
          "HTG": {
            "displayName": "ܓܘܪܕ ܕܗܐܝܬܝ",
            "displayName-count-one": "ܓܘܪܕ ܕܗܐܝܬܝ",
            "displayName-count-other": "ܓܘܪ̈ܕܐ ܕܗܐܝܬܝ"
          },
          "HUF": {
            "symbol-alt-narrow": "Ft"
          },
          "IDR": {
            "symbol-alt-narrow": "Rp"
          },
          "ILS": {
            "displayName": "ܬܩܠܐ ܚܕܬܐ ܕܐܝܣܪܐܝܠ",
            "displayName-count-one": "ܬܩܠܐ ܚܕܬܐ ܕܐܝܣܪܐܝܠ",
            "displayName-count-other": "ܬܩ̈ܠܐ ܚܕ̈ܬܐ ܕܐܝܣܪܐܝܠ",
            "symbol": "₪",
            "symbol-alt-narrow": "₪"
          },
          "INR": {
            "symbol": "₹",
            "symbol-alt-narrow": "₹"
          },
          "IQD": {
            "displayName": "ܕܝܢܪܐ ܕܥܝܪܐܩ",
            "displayName-count-one": "ܕܝܢܪܐ ܕܥܝܪܐܩ",
            "displayName-count-other": "ܕܝܢܪ̈ܐ ܕܥܝܪܐܩ"
          },
          "ISK": {
            "symbol-alt-narrow": "kr"
          },
          "JMD": {
            "displayName": "ܕܘܠܪ ܕܓܡܝܟܐ",
            "displayName-count-one": "ܕܘܠܪ ܕܓܡܝܟܐ",
            "displayName-count-other": "ܕܘܠܪ̈ܐ ܕܓܡܝܟܐ",
            "symbol-alt-narrow": "$"
          },
          "JOD": {
            "displayName": "ܕܝܢܪܐ ܕܝܘܪܕܢܢ",
            "displayName-count-one": "ܕܝܢܪܐ ܕܝܘܪܕܢܢ",
            "displayName-count-other": "ܕܝܢܪ̈ܐ ܕܝܘܪܕܢܢ"
          },
          "JPY": {
            "symbol": "JP¥",
            "symbol-alt-narrow": "¥"
          },
          "KGS": {
            "symbol-alt-narrow": "⃀"
          },
          "KHR": {
            "symbol-alt-narrow": "៛"
          },
          "KMF": {
            "symbol-alt-narrow": "CF"
          },
          "KPW": {
            "displayName": "ܘܘܢ ܕܟܘܪܝܐ ܓܪܒܝܝܬܐ",
            "displayName-count-one": "ܘܘܢ ܕܟܘܪܝܐ ܓܪܒܝܝܬܐ",
            "displayName-count-other": "ܘܘܢ̈ܐ ܕܟܘܪܝܐ ܓܪܒܝܝܬܐ",
            "symbol-alt-narrow": "₩"
          },
          "KRW": {
            "displayName": "ܘܘܢ ܕܟܘܪܝܐ ܬܝܡܢܝܬܐ",
            "displayName-count-one": "ܘܘܢ ܕܟܘܪܝܐ ܬܝܡܢܝܬܐ",
            "displayName-count-other": "ܘܘܢ̈ܐ ܕܟܘܪܝܐ ܬܝܡܢܝܬܐ",
            "symbol": "₩",
            "symbol-alt-narrow": "₩"
          },
          "KWD": {
            "displayName": "ܕܝܢܪܐ ܕܟܘܝܬ",
            "displayName-count-one": "ܕܝܢܪܐ ܕܟܘܝܬ",
            "displayName-count-other": "ܕܝܢܪ̈ܐ ܕܟܘܝܬ"
          },
          "KYD": {
            "displayName": "ܕܘܠܪ ܕܓܙܪ̈ܬܐ ܕܟܐܝܡܐܢ",
            "displayName-count-one": "ܕܘܠܪ ܕܓܙܪ̈ܬܐ ܕܟܐܝܡܐܢ",
            "displayName-count-other": "ܕܘܠܪ̈ܐ ܕܓܙܪ̈ܬܐ ܕܟܐܝܡܐܢ",
            "symbol-alt-narrow": "$"
          },
          "KZT": {
            "symbol-alt-narrow": "₸"
          },
          "LAK": {
            "symbol-alt-narrow": "₭"
          },
          "LBP": {
            "displayName": "ܠܝܛܪܐ ܕܠܒܢܢ",
            "displayName-count-one": "ܠܝܛܪܐ ܕܠܒܢܢ",
            "displayName-count-other": "ܠܝܛܪ̈ܐ ܕܠܒܢܢ",
            "symbol-alt-narrow": "L£"
          },
          "LKR": {
            "symbol-alt-narrow": "Rs"
          },
          "LRD": {
            "symbol-alt-narrow": "$"
          },
          "LTL": {
            "symbol-alt-narrow": "Lt"
          },
          "LVL": {
            "symbol-alt-narrow": "Ls"
          },
          "LYD": {
            "displayName": "ܕܝܢܪܐ ܕܠܘܒܐ",
            "displayName-count-one": "ܕܝܢܪܐ ܕܠܘܒܐ",
            "displayName-count-other": "ܕܝܢܪ̈ܐ ܕܠܘܒܐ"
          },
          "MAD": {
            "displayName": "ܕܪܗܡ ܕܡܓܪܒ",
            "displayName-count-one": "ܕܪܗܡ ܕܡܓܪܒ",
            "displayName-count-other": "ܕܪ̈ܗܡܐ ܕܡܓܪܒ"
          },
          "MGA": {
            "symbol-alt-narrow": "Ar"
          },
          "MKD": {
            "displayName": "ܕܝܢܪܐ ܕܡܩܕܘܢܝܐ",
            "displayName-count-one": "ܕܝܢܪܐ ܕܡܩܕܘܢܝܐ",
            "displayName-count-other": "ܕܝܢܪ̈ܐ ܕܡܩܕܘܢܝܐ"
          },
          "MMK": {
            "symbol-alt-narrow": "K"
          },
          "MNT": {
            "symbol-alt-narrow": "₮"
          },
          "MUR": {
            "symbol-alt-narrow": "Rs"
          },
          "MXN": {
            "displayName": "ܦܝܣܘ ܕܡܟܣܝܟܘ",
            "displayName-count-one": "ܦܝܣܘ ܕܡܟܣܝܟܘ",
            "displayName-count-other": "ܦܝ̈ܣܘܣ ܕܡܟܣܝܟܘ",
            "symbol": "MX$",
            "symbol-alt-narrow": "$"
          },
          "MYR": {
            "symbol-alt-narrow": "RM"
          },
          "NAD": {
            "symbol-alt-narrow": "$"
          },
          "NGN": {
            "symbol-alt-narrow": "₦"
          },
          "NIO": {
            "displayName": "ܩܘܪܕܘܒܝ ܕܢܝܟܐܪܐܓܘܐ",
            "displayName-count-one": "ܩܘܪܕܘܒܝ ܕܢܝܟܐܪܐܓܘܐ",
            "displayName-count-other": "ܩܘܪ̈ܕܘܒܐ ܕܢܝܟܐܪܐܓܘܐ",
            "symbol-alt-narrow": "C$"
          },
          "NOK": {
            "symbol-alt-narrow": "kr"
          },
          "NPR": {
            "symbol-alt-narrow": "Rs"
          },
          "NZD": {
            "symbol": "NZ$",
            "symbol-alt-narrow": "$"
          },
          "PAB": {
            "displayName": "ܒܐܠܒܘܐ ܕܦܐܢܡܐ",
            "displayName-count-one": "ܒܐܠܒܘܐ ܕܦܐܢܡܐ",
            "displayName-count-other": "ܒܐܠܒܘ̈ܐ ܕܦܐܢܡܐ"
          },
          "PHP": {
            "displayName": "ܦܝܣܘ ܕܦܝܠܝܦܝܐ",
            "displayName-count-one": "ܦܝܣܘ ܕܦܝܠܝܦܝܐ",
            "displayName-count-other": "ܦܝ̈ܣܘܣ ܕܦܝܠܝܦܝܐ",
            "symbol": "₱",
            "symbol-alt-narrow": "₱"
          },
          "PKR": {
            "symbol-alt-narrow": "Rs"
          },
          "PLN": {
            "symbol-alt-narrow": "zł"
          },
          "PYG": {
            "symbol-alt-narrow": "₲"
          },
          "RON": {
            "symbol-alt-narrow": "lei"
          },
          "RSD": {
            "displayName": "ܕܝܢܪܐ ܕܣܪܒܝܐ",
            "displayName-count-one": "ܕܝܢܪܐ ܕܣܪܒܝܐ",
            "displayName-count-other": "ܕܝܢܪ̈ܐ ܕܣܪܒܝܐ"
          },
          "RUB": {
            "symbol-alt-narrow": "₽"
          },
          "RWF": {
            "symbol-alt-narrow": "RF"
          },
          "SAR": {
            "symbol-alt-variant": "⃁"
          },
          "SBD": {
            "displayName": "ܕܘܠܪ ܕܓܙܪ̈ܬܐ ܕܫܠܝܡܘܢ",
            "displayName-count-one": "ܕܘܠܪ ܕܓܙܪ̈ܬܐ ܕܫܠܝܡܘܢ",
            "displayName-count-other": "ܕܘܠܪ̈ܐ ܕܓܙܪ̈ܬܐ ܕܫܠܝܡܘܢ",
            "symbol-alt-narrow": "$"
          },
          "SDG": {
            "displayName": "ܠܝܛܪܐ ܕܣܘܕܐܢ",
            "displayName-count-one": "ܠܝܛܪܐ ܕܣܘܕܐܢ",
            "displayName-count-other": "ܠܝܛܪ̈ܐ ܕܣܘܕܐܢ"
          },
          "SEK": {
            "symbol-alt-narrow": "kr"
          },
          "SGD": {
            "displayName": "ܕܘܠܪ ܕܣܝܢܓܐܦܘܪ",
            "displayName-count-one": "ܕܘܠܪ̈ܐ ܕܣܝܢܓܐܦܘܪ",
            "displayName-count-other": "ܕܘܠܪ̈ܐ ܕܣܝܢܓܐܦܘܪ",
            "symbol-alt-narrow": "$"
          },
          "SHP": {
            "symbol-alt-narrow": "£"
          },
          "SRD": {
            "symbol-alt-narrow": "$"
          },
          "SSP": {
            "symbol-alt-narrow": "£"
          },
          "STN": {
            "symbol-alt-narrow": "Db"
          },
          "SYP": {
            "displayName": "ܠܝܛܪܐ ܕܣܘܪܝܐ",
            "displayName-count-one": "ܠܝܛܪܐ ܕܣܘܪܝܐ",
            "displayName-count-other": "ܠܝܛܪ̈ܐ ܕܣܘܪܝܐ",
            "symbol": "ل.س.‏",
            "symbol-alt-narrow": "£"
          },
          "THB": {
            "symbol-alt-narrow": "฿"
          },
          "TND": {
            "displayName": "ܕܝܢܪܐ ܕܬܘܢܣ",
            "displayName-count-one": "ܕܝܢܪܐ ܕܬܘܢܣ",
            "displayName-count-other": "ܕܝܢܪ̈ܐ ܕܬܘܢܣ"
          },
          "TOP": {
            "symbol-alt-narrow": "T$"
          },
          "TRY": {
            "displayName": "ܠܝܛܪܐ ܕܬܘܪܟܝܐ",
            "displayName-count-one": "ܠܝܛܪܐ ܕܬܘܪܟܝܐ",
            "displayName-count-other": "ܠܝܛܪ̈ܐ ܕܬܘܪܟܝܐ",
            "symbol-alt-narrow": "₺",
            "symbol-alt-variant": "TL"
          },
          "TTD": {
            "displayName": "ܕܘܠܪ ܕܬܪܝܢܝܕܐܕ ܘܬܘܒܐܓܘ",
            "displayName-count-one": "ܕܘܠܪ ܕܬܪܝܢܝܕܐܕ ܘܬܘܒܐܓܘ",
            "displayName-count-other": "ܕܘܠܪ̈ܐ ܕܬܪܝܢܝܕܐܕ ܘܬܘܒܐܓܘ",
            "symbol-alt-narrow": "$"
          },
          "TWD": {
            "symbol": "NT$",
            "symbol-alt-narrow": "$"
          },
          "UAH": {
            "symbol-alt-narrow": "₴"
          },
          "USD": {
            "displayName": "ܕܘܠܪ ܕܐܘܚܕܢ̈ܐ ܡܚܘܝܕ̈ܐ",
            "displayName-count-one": "ܕܘܠܪ ܕܐܘܚܕܢ̈ܐ ܡܚܘܝܕ̈ܐ",
            "displayName-count-other": "ܕܘܠܪ̈ܐ ܕܐܘܚܕܢ̈ܐ ܡܚܘܝܕ̈ܐ",
            "symbol": "US$",
            "symbol-alt-narrow": "$"
          },
          "UYU": {
            "displayName": "ܦܝܣܘ ܕܐܘܪܘܓܘܐܝ",
            "displayName-count-one": "ܦܝܣܘ ܕܐܘܪܘܓܘܐܝ",
            "displayName-count-other": "ܦܝ̈ܣܘܣ ܕܐܘܪܘܓܘܐܝ",
            "symbol-alt-narrow": "$"
          },
          "VEF": {
            "symbol-alt-narrow": "Bs"
          },
          "VND": {
            "displayName": "ܕܘܢܓ ܕܒܝܬܢܐܡ",
            "displayName-count-one": "ܕܘܢܓ ܕܒܝܬܢܐܡ",
            "displayName-count-other": "ܕܘܢܓ̈ܐ ܕܒܝܬܢܐܡ",
            "symbol": "₫",
            "symbol-alt-narrow": "₫"
          },
          "XAF": {
            "symbol": "FCFA"
          },
          "XCD": {
            "displayName": "ܕܘܠܪ ܕܡܕܢܚ ܟܐܪܝܒܐ",
            "displayName-count-one": "ܕܘܠܪ ܕܡܕܢܚ ܟܐܪܝܒܐ",
            "displayName-count-other": "ܕܘܠܪ̈ܐ ܕܡܕܢܚ ܟܐܪܝܒܐ",
            "symbol": "EC$",
            "symbol-alt-narrow": "$"
          },
          "XCG": {
            "displayName": "ܦܠܘܪܝܢ ܕܩܘܒܐ",
            "displayName-count-one": "ܦܠܘܪܝܢ ܕܩܘܒܐ",
            "displayName-count-other": "ܦܠܘܪ̈ܝܢܐ ܕܩܘܒܐ",
            "symbol": "Cg."
          },
          "XOF": {
            "symbol": "F CFA"
          },
          "XPF": {
            "symbol": "CFPF"
          },
          "XXX": {
            "displayName": "ܟܣܦܐ ܠܐ ܝܕܝܥܐ",
            "displayName-count-one": "(ܟܣܦܐ ܠܐ ܝܕܝܥܐ)",
            "displayName-count-other": "(ܟܣܦܐ ܠܐ ܝܕܝܥܐ)",
            "symbol": "¤"
          },
          "ZAR": {
            "symbol-alt-narrow": "R"
          },
          "ZMW": {
            "symbol-alt-narrow": "ZK"
          }
        }
      }
    }
  }
}
